setup.py
testmodule2/__init__.py
testmodule2.egg-info/PKG-INFO
testmodule2.egg-info/SOURCES.txt
testmodule2.egg-info/dependency_links.txt
testmodule2.egg-info/requires.txt
testmodule2.egg-info/top_level.txt